pylichat/__init__.py
pylichat/__main__.py
pylichat/client.py
pylichat/symbol.py
pylichat/toolkit.py
pylichat/update.py
pylichat/wire.py
pylichat/spec/.dir-locals.el
pylichat/spec/.gitignore
pylichat/spec/LICENSE
pylichat/spec/README.mess
pylichat/spec/compile.lisp
pylichat/spec/lichat.sexpr
pylichat/spec/logo.svg
pylichat/spec/shirakumo.mess
pylichat/spec/shirakumo.sexpr
pylichat-1.4.dist-info/METADATA
pylichat-1.4.dist-info/WHEEL
pylichat-1.4.dist-info/entry_points.txt
pylichat-1.4.dist-info/licenses/LICENSE
pylichat-1.4.dist-info/RECORD
